faqtory/__init__.py
faqtory/__main__.py
faqtory/cli.py
faqtory/models.py
faqtory/questions.py
faqtory/templates.py
faqtory-1.1.3.dist-info/LICENSE
faqtory-1.1.3.dist-info/METADATA
faqtory-1.1.3.dist-info/WHEEL
faqtory-1.1.3.dist-info/entry_points.txt
faqtory-1.1.3.dist-info/RECORD
